{
    "Andere Aufenthaltserlaubnis i.S. des AufenthG": "مجوز اقامت به دلایل دیگرطبق قانون اساسی آلمان",
    "Anlage 2 - Ausländer -": "ضمیمه ۲ ـ خارجیها",
    "Anschrift": "آدرس",
    "Asyl": "پناهندگی",
    "Aufenthaltsdokumente": "مدارک اقامتی",
    "Aufenthaltserlaubnis wg. des Krieges im Heimatland nach § 23 Abs. 1 oder § 24 oder nach § 25 Abs. 4 Satz1, Abs. 4 a, 4 b oder Abs.5 AufenthG": "مجوز اقامت به دلیل شرایط جنگی در وطن متقاضی ٫مطابق پاراگراف ۲۳ بند ۱ از قانون اساسی آلمان یا پاراگراف ۲۴ یا پاراگراف ۲۵ بند ۴ خط ٫۱بند ۴آ۴٫ب یا بند ۵ از قانون اقامت آلمان",
    "Aufenthaltsgestattung zur Durchführung eines Asylverfahrens": "مجوز اقامت برای بررسی درخواست پناهندگی",
    "Aussetzung der Abschiebung (Duldung)": "تعلیق اخراج متقاضی ازآلمان",
    "Ausübung einer Erwerbstätigkeit": "اجازه کار و فعالیت",
    "Datum": "تاریخ آن",
    "Datum und Unterschrift d. Antragstellers/Antragstellerin": "تاریخ و امضاء درخواست کننده",
    "Einreise": "ورود به آلمان",
    "Fiktionsbescheinigung „gilt Abschiebung als ausgesetzt“": "مجوز اقامت موقت با درج عبارت ٍ اخراج متقاضی منتفی است ً",
    "Fiktionsbescheinigung „gilt Aufenthalt als erlaubt“ oder „gilt Aufenthaltstitel als fortbestehend“": "مجوز اقامت موقت با درج عبارت ٍ متقاضی اجازه اقامت دارد ً یا ٍ اجازه اقامت متقاضی تمدید شده است ً",
    "Folgeantrag": "ادامه ی درخواست",
    "Geschäftszeichen": "شماره پیگیری",
    "Grenzübertrittsbescheinigung": "گواهی برای ترک آلمان",
    "Gründe für den jetzigen Aufenthalt; ggf. Gründe, weshalb ich nicht in mein Heimatland zurückkehren kann:": "دلایل اقامت فعلی، به ویژه دلایلی که امکان بازگشت به وطن خود را ندارید",
    "Ja": "خیر",
    "Klage eingereicht": "شکواییه تسلیم شده",
    "Klage eingereicht am ... ;bevollmächtigter Rechtsanwalt (Name und Anschrift)": "شکواییه در تاریخ .... تسلیم شده است؛ وکیل دارای وکالت تام (نام و آدرس)",
    "Name": "نام و نام خانوادگی",
    "Name, Vorname": "نام ٫نام خانوادگی",
    "Nein": "بله",
    "Niederlassungserlaubnis": "مجوز اقامت",
    "Pass-Nr.:": "شماره گذرنامه :",
    "Passeinzugsbescheinigung": "گواهی توقیف پاسپورت",
    "Visum auf Einladung von": "دارنده ویزای مدعو از",
    "Vorlage einer Verpflichtungserklärung": "ارائه ضمانتنامه مالی برای شهروندی ازجهان سوم",
    "Zeitpunkt der letzten Einreise in die BRD": "زمان آخرین ورود به آلمان",
    "Zeitraum": "مدت اقامت",
    "Zum Antrag vom": "موضوع درخواست",
    "Zweitantrag": "درخواست مجدد",
    "\\- unbefristet -": "- اقامت نامحدود -",
    "abgelehnt am": "تاریخ رد درخواست",
    "am": "تاریخ درخواست",
    "ausgestellt am": "تاریخ صدور:",
    "beantragt": "درخواست شده",
    "befristet bis": "به مدت محدود تا تاریخ ...",
    "bevollmächtigter Rechtsanwalt (Name und Anschrift)": "وکیل دارای اختیار تام (نام و آدرس)",
    "erlaubt": "دارد",
    "frühere Aufenthalte in der BRD": "اقامتهای قبلی در آلمان",
    "gültig bis": "تاریخ انقضاء",
    "letzter gewöhnlicher Aufenthalt im Ausland (Ort/Land)": "آخرین اقامت بلندمدت درخارج ازکشور(شهر،کشور)",
    "mit Ausreisefrist bis zum": "حداکثر تا تاریخ...",
    "nicht beantragt": "درخواست نشده",
    "nicht erhalten": "دریافت نشده است",
    "nicht erlaubt": "ندارد",
    "unbefristet": "به مدت نامحدود",
    "von (Bundesagentur) für Arbeit": "اجازه از سوی اداره کار صادر شده",
    "von (Dienststelle)": "ارگان صادرکننده"
}