{
    "Anrede": "اللقب (دكتور, استاذ الخ)",
    "Antrag stellen": "تقديم الطلب",
    "Asylbewerberleistung": "مساعدات اللاجئين",
    "Bitte auswählen": "يرجى الاختيار",
    "Drucken": "إطبع",
    "Familienstand": "الحالة الاجتماعية",
    "Geburtsdatum": "تاريخ الميلاد",
    "Ja": "نعم",
    "Korrigieren": "تصحيح",
    "Nein": "لا",
    "Vorname": "الاسم",
    "Weiter": "التالي",
    "eingetragene Lebenspartnerschaft": "شريك حياة مسجل",
    "geschieden": "مطلق",
    "ledig": "أعزب",
    "verheiratet": "متزوج",
    "verwitwet": "أرمل"
}