{
  "(Unterschrift des Kindes)": "(Signature de l'enfant)",
  "Familienstand:": "Situation de famille :",
  "Geburtsdatum": "date de naissance",
  "Kindergeld-Nr.": "N° d'allocataire",
  "Name und Vorname des/der Kindergeldberechtigten": "Nom et prénom du(des) bénéficiaire(s) des prestations pour enfant",
  "Telefonische Rückfrage tagsüber unter Nr.:": "Pour toute question, téléphonez pendant la journée au :",
  "Vorname": "Prénom",
  "bis": "au",
  "dauernd getrennt lebend": "durablement séparé(e)",
  "geschieden": "divorcé(e)",
  "in eingetragener Lebenspartnerschaft lebend": "en partenariat enregistré",
  "ledig": "célibataire",
  "nein": "non",
  "seit": "depuis",
  "verheiratet": "marié(e)",
  "verwitwet": "veuf(ve)"
}